cpms_client/__init__.py
cpms_client-0.1.2.dist-info/licenses/LICENSE
cpms_client-0.1.2.dist-info/METADATA
cpms_client-0.1.2.dist-info/WHEEL
cpms_client-0.1.2.dist-info/top_level.txt
cpms_client-0.1.2.dist-info/RECORD
