Metadata-Version: 2.4
Name: cpms_client
Version: 0.1.2
Summary: Python wrapper for the CPMS HTTP API
Author: Lehel Kovach
License: MIT
Project-URL: Homepage, https://github.com/lehelkovach/cpms
Project-URL: Repository, https://github.com/lehelkovach/cpms
Keywords: cpms,api,client,automation
Requires-Python: >=3.9
